SciFiReaders/__init__.py
SciFiReaders/__version__.py
SciFiReaders/ingestor.py
SciFiReaders/readers/__init__.py
SciFiReaders/readers/SID/Nsid_reader.py
SciFiReaders/readers/SID/Usid_reader.py
SciFiReaders/readers/SID/__init__.py
SciFiReaders/readers/SID/hdf_utils.py
SciFiReaders/readers/converters/__init__.py
SciFiReaders/readers/converters/hyperspy.py
SciFiReaders/readers/generic/__init__.py
SciFiReaders/readers/generic/image.py
SciFiReaders/readers/microscopy/__init__.py
SciFiReaders/readers/microscopy/em/__init__.py
SciFiReaders/readers/microscopy/em/sem/__init__.py
SciFiReaders/readers/microscopy/em/sem/bruker_reader.py
SciFiReaders/readers/microscopy/em/sem/edax_reader.py
SciFiReaders/readers/microscopy/em/tem/__init__.py
SciFiReaders/readers/microscopy/em/tem/dm3_reader.py
SciFiReaders/readers/microscopy/em/tem/dm_reader.py
SciFiReaders/readers/microscopy/em/tem/emd_reader.py
SciFiReaders/readers/microscopy/em/tem/mrc_reader.py
SciFiReaders/readers/microscopy/em/tem/nion_reader.py
SciFiReaders/readers/microscopy/em/tem/stem/__init__.py
SciFiReaders/readers/microscopy/ion/__init__.py
SciFiReaders/readers/microscopy/spm/__init__.py
SciFiReaders/readers/microscopy/spm/afm/AR_hdf5.py
SciFiReaders/readers/microscopy/spm/afm/__init__.py
SciFiReaders/readers/microscopy/spm/afm/axz.py
SciFiReaders/readers/microscopy/spm/afm/base_utils.py
SciFiReaders/readers/microscopy/spm/afm/bruker_nano.py
SciFiReaders/readers/microscopy/spm/afm/gwyddion.py
SciFiReaders/readers/microscopy/spm/afm/igor_ibw.py
SciFiReaders/readers/microscopy/spm/afm/mdt.py
SciFiReaders/readers/microscopy/spm/afm/nanosurf.py
SciFiReaders/readers/microscopy/spm/afm/pifm.py
SciFiReaders/readers/microscopy/spm/afm/wsxm.py
SciFiReaders/readers/microscopy/spm/stm/__init__.py
SciFiReaders/readers/microscopy/spm/stm/nanonis_3ds.py
SciFiReaders/readers/microscopy/spm/stm/nanonis_base.py
SciFiReaders/readers/microscopy/spm/stm/nanonis_dat.py
SciFiReaders/readers/microscopy/spm/stm/nanonis_sxm.py
scifireaders-0.12.4.dist-info/licenses/LICENSE
scifireaders-0.12.4.dist-info/METADATA
scifireaders-0.12.4.dist-info/WHEEL
scifireaders-0.12.4.dist-info/top_level.txt
scifireaders-0.12.4.dist-info/RECORD
