Metadata-Version: 2.4
Name: SciFiReaders
Version: 0.12.4
Summary: Tools for extracting data and metadata from scientific data files
Author-email: Pycroscopy contributors <pycroscopy@gmail.com>
License: MIT
Project-URL: Homepage, https://pycroscopy.github.io/SciFiReaders/about.html
Keywords: imaging,spectra,multidimensional,scientific
Classifier: Development Status :: 3 - Alpha
Classifier: Environment :: Console
Classifier: Intended Audience :: Science/Research
Classifier: License :: OSI Approved :: MIT License
Classifier: Natural Language :: English
Classifier: Operating System :: OS Independent
Classifier: Programming Language :: Python :: 3
Classifier: Programming Language :: Python :: 3.9
Classifier: Programming Language :: Python :: 3.10
Classifier: Programming Language :: Python :: 3.11
Classifier: Programming Language :: Python :: Implementation :: CPython
Classifier: Topic :: Scientific/Engineering :: Information Analysis
Requires-Python: >=3.9
License-File: LICENSE
Requires-Dist: setuptools
Requires-Dist: numpy
Requires-Dist: toolz
Requires-Dist: cytoolz
Requires-Dist: dask>=2.20.0
Requires-Dist: sidpy>=0.11.2
Requires-Dist: numba
Requires-Dist: ipython>=7.1.0
Requires-Dist: pyUSID
Requires-Dist: gdown
Requires-Dist: mrcfile
Requires-Dist: pycroscopy-gwyfile
Requires-Dist: scipy>=1.11
Provides-Extra: hyperspy
Requires-Dist: hyperspy; extra == "hyperspy"
Provides-Extra: igor2
Requires-Dist: igor2; extra == "igor2"
Provides-Extra: sid
Requires-Dist: pyUSID; extra == "sid"
Requires-Dist: pyNSID; extra == "sid"
Provides-Extra: image
Requires-Dist: pillow; extra == "image"
Requires-Dist: tifffile; extra == "image"
Provides-Extra: test
Requires-Dist: pytest; extra == "test"
Requires-Dist: hyperspy; extra == "test"
Requires-Dist: pyUSID; extra == "test"
Requires-Dist: gdown; extra == "test"
Dynamic: license-file
